{
  "intents": [
    {
      "intent": "RawText",
      "slots": [
        {
          "name": "Text",
          "type": "AMAZON.LITERAL"
        }
      ]
    },
    {
      "intent": "ReadAgenda"
    },
    {
      "intent": "NextAgendaItem"
    },
    {
      "intent": "RecordAgendaItem",
      "slots": [
        {
          "name": "AgendaItem",
          "type": "AMAZON.LITERAL"
        }
      ]
    },
    {
      "intent": "ReadActionList"
    },
    {
      "intent": "RecordActionItem",
      "slots": [
        {
          "name": "ActionItem",
          "type": "AMAZON.LITERAL"
        }
      ]
    },
    {
      "intent": "RecordMotion",
      "slots": [
        {
          "name": "Motion",
          "type": "AMAZON.LITERAL"
        }
      ]
    },
    {
      "intent": "CastVote"
    },
    {
      "intent": "AMAZON.NoIntent"
    },
    {
      "intent": "AMAZON.YesIntent"
    },
    {
      "intent": "AddParticipant",
      "slots": [
        {
          "name": "Participant",
          "type": "AMAZON.LITERAL"
        }
      ]
    },
    {
      "intent": "RecordNote",
      "slots": [
        {
          "name": "Note",
          "type": "AMAZON.LITERAL"
        }
      ]
    },
    {
      "intent": "WhoAmI",
      "slots": [
        {
          "name": "Text",
          "type": "AMAZON.LITERAL"
        }
      ]
    }

  ]
}
